pyduq/SQLTools.py
pyduq/__init__.py
pyduq/abstractduqvalidator.py
pyduq/boxplot.py
pyduq/dataprofile.py
pyduq/dataqualityerror.py
pyduq/duqerror.py
pyduq/duqvalidator.py
pyduq/expressionbuilder.py
pyduq/filetools.py
pyduq/metautils.py
pyduq/patterns.py
pyduq/pyDUQMain.py
pyduq/doc/EBNF-Visualizer.exe
pyduq/doc/__init__.py
pyduq/doc/expression.GIF
pyduq/doc/ident.GIF
pyduq/doc/int.GIF
pyduq/doc/pyduq Grammar v1.1.docx
pyduq/doc/pyduq Grammar v1.1.ebnf
pyduq/doc/pyduq.png
pyduq/doc/statement.GIF
pyduq/doc/term.GIF
pyduq/tests/README.txt
pyduq/tests/SA development application register.csv
pyduq/tests/SA development application register_meta.json
pyduq/tests/SA development application register_profile.xlsx
pyduq/tests/SA development application register_summary.xlsx
pyduq/tests/__init__.py
pyduq/tests/bubble_chart.html
pyduq/tests/counters.xlsx
pyduq/tests/summary.xlsx
pyduq/tests/testTemplate.py
pyduq/tests/testValidator.ipynb
pyduq/tests/validate.bat
pyduq/tests/wget.exe
pyduq-1.0.7.dist-info/LICENSE
pyduq-1.0.7.dist-info/METADATA
pyduq-1.0.7.dist-info/WHEEL
pyduq-1.0.7.dist-info/top_level.txt
pyduq-1.0.7.dist-info/RECORD
