Metadata-Version: 2.1
Name: pyduq
Version: 1.0.7
Summary: A tool to validate data accoridng to the University of Queensland conformed dimensions of data quality.
Home-page: https://github.com/sjdowney/pyduq
Author: Shane J. Downey
Author-email: shane.downey69au@gmail.com
Classifier: Programming Language :: Python :: 3
Classifier: License :: Freely Distributable
Classifier: Operating System :: OS Independent
Requires-Python: >=3.4
License-File: LICENSE
Requires-Dist: dicttoxml
Requires-Dist: plotly
Requires-Dist: pyodbc
Requires-Dist: prettytable
Requires-Dist: openpyxl
Requires-Dist: sklearn
Requires-Dist: scipy
Requires-Dist: nltk
Requires-Dist: unidecode
